jupyter_weav_app_four/__init__.py
jupyter_weav_app_four/_version.py
jupyter_weav_app_four/labextension/package.json
jupyter_weav_app_four/labextension/static/338.097a821a5ed3723e6cc7.js
jupyter_weav_app_four/labextension/static/356.aade6baa73bb6f6c1b59.js
jupyter_weav_app_four/labextension/static/356.aade6baa73bb6f6c1b59.js.LICENSE.txt
jupyter_weav_app_four/labextension/static/413.d58104929a8a867a3799.js
jupyter_weav_app_four/labextension/static/413.d58104929a8a867a3799.js.LICENSE.txt
jupyter_weav_app_four/labextension/static/534.9fb8d9d14e63804f651a.js
jupyter_weav_app_four/labextension/static/669.2c9508a5bbf86052096c.js
jupyter_weav_app_four/labextension/static/957.8671b52d1b3b017a7032.js
jupyter_weav_app_four/labextension/static/957.8671b52d1b3b017a7032.js.LICENSE.txt
jupyter_weav_app_four/labextension/static/975.005f8862f4f29133efe2.js
jupyter_weav_app_four/labextension/static/975.005f8862f4f29133efe2.js.LICENSE.txt
jupyter_weav_app_four/labextension/static/remoteEntry.d50f934e82782ff58220.js
jupyter_weav_app_four/labextension/static/style.js
jupyter_weav_app_four-0.1.0.data/data/share/jupyter/labextensions/jupyter_weav_app_four/install.json
jupyter_weav_app_four-0.1.0.data/data/share/jupyter/labextensions/jupyter_weav_app_four/package.json
jupyter_weav_app_four-0.1.0.data/data/share/jupyter/labextensions/jupyter_weav_app_four/static/338.097a821a5ed3723e6cc7.js
jupyter_weav_app_four-0.1.0.data/data/share/jupyter/labextensions/jupyter_weav_app_four/static/356.aade6baa73bb6f6c1b59.js
jupyter_weav_app_four-0.1.0.data/data/share/jupyter/labextensions/jupyter_weav_app_four/static/356.aade6baa73bb6f6c1b59.js.LICENSE.txt
jupyter_weav_app_four-0.1.0.data/data/share/jupyter/labextensions/jupyter_weav_app_four/static/413.d58104929a8a867a3799.js
jupyter_weav_app_four-0.1.0.data/data/share/jupyter/labextensions/jupyter_weav_app_four/static/413.d58104929a8a867a3799.js.LICENSE.txt
jupyter_weav_app_four-0.1.0.dist-info/LICENSE
jupyter_weav_app_four-0.1.0.dist-info/METADATA
jupyter_weav_app_four-0.1.0.dist-info/WHEEL
jupyter_weav_app_four-0.1.0.dist-info/top_level.txt
jupyter_weav_app_four-0.1.0.dist-info/RECORD
