Metadata-Version: 2.1
Name: jupyter-weav-app-four
Version: 0.1.0
Summary: Test WEAV AI
Home-page: https://github.com/chaitanyamoon/jupyter_weav_app_four
Author: chaitanya
Author-email: chaitanya.moon@konverge.ai
License: BSD-3-Clause
Keywords: Jupyter,JupyterLab,JupyterLab3
Platform: Linux
Platform: Mac OS X
Platform: Windows
Classifier: License :: OSI Approved :: BSD License
Classifier: Programming Language :: Python
Classifier: Programming Language :: Python :: 3
Classifier: Programming Language :: Python :: 3.6
Classifier: Programming Language :: Python :: 3.7
Classifier: Programming Language :: Python :: 3.8
Classifier: Programming Language :: Python :: 3.9
Classifier: Framework :: Jupyter
Requires-Python: >=3.6
Requires-Dist: jupyter-server (<2,>=1.6)
